lucidwallet/__init__.py
lucidwallet/__main__.py
lucidwallet/app.css
lucidwallet/datastore/__init__.py
lucidwallet/datastore/fluxwallet_datastore.py
lucidwallet/entrypoint.py
lucidwallet/events/__init__.py
lucidwallet/helpers/__init__.py
lucidwallet/images/flux_200x200.png
lucidwallet/screens/__init__.py
lucidwallet/screens/address_book.py
lucidwallet/screens/address_book_overlay.py
lucidwallet/screens/create_wallet.py
lucidwallet/screens/get_encryption_password.py
lucidwallet/screens/import_from_mnemonic.py
lucidwallet/screens/import_key_to_wallet.py
lucidwallet/screens/keychain_overlay.py
lucidwallet/screens/loading.py
lucidwallet/screens/mnemonic_overlay.py
lucidwallet/screens/no_wallets.py
lucidwallet/screens/sendtx_overlay.py
lucidwallet/screens/sign_message_overlay.py
lucidwallet/screens/tx_sent_overlay.py
lucidwallet/screens/txoverlay.py
lucidwallet/screens/wallet.css
lucidwallet/screens/wallet_landing.py
lucidwallet/ssl_win/libeay32.dll
lucidwallet/ssl_win/ssleay32.dll
lucidwallet/tests/test.py
lucidwallet/widgets/__init__.py
lucidwallet/widgets/network_bar.py
lucidwallet/widgets/send.py
lucidwallet/widgets/send_working.py
lucidwallet/widgets/test_non_async.py
lucidwallet/widgets/top_bar.py
lucidwallet/widgets/transactions.py
lucidwallet/widgets/transactions_old.py
lucidwallet/widgets/tx_loading.py
lucidwallet-0.2.21.dist-info/LICENSE
lucidwallet-0.2.21.dist-info/METADATA
lucidwallet-0.2.21.dist-info/WHEEL
lucidwallet-0.2.21.dist-info/entry_points.txt
lucidwallet-0.2.21.dist-info/RECORD
