Metadata-Version: 2.1
Name: lucidwallet
Version: 0.2.21
Summary: A Graphical interface for FluxWallet
License: bsd 3-clause
Author: David White
Author-email: dr.white.nz@gmail.com
Requires-Python: >=3.10,<4.0
Classifier: License :: Other/Proprietary License
Classifier: Programming Language :: Python :: 3
Classifier: Programming Language :: Python :: 3.10
Classifier: Programming Language :: Python :: 3.11
Requires-Dist: Pillow (>=10.0.0,<11.0.0)
Requires-Dist: aiohttp (>=3.8.5,<4.0.0)
Requires-Dist: fluxwallet (>=0.2.3,<0.3.0)
Requires-Dist: keyring (>=24.2.0,<25.0.0)
Requires-Dist: packaging (>=23.1,<24.0)
Requires-Dist: pyperclip (>=1.8.2,<2.0.0)
Requires-Dist: python-bitcoinlib (==0.12.2)
Requires-Dist: python-socketio[asyncio-client] (==4.6.1)
Requires-Dist: textual (>=0.32.0,<0.33.0)
